README.md
pyproject.toml
src/inmanta_dev_dependencies/__init__.py
src/inmanta_dev_dependencies.egg-info/PKG-INFO
src/inmanta_dev_dependencies.egg-info/SOURCES.txt
src/inmanta_dev_dependencies.egg-info/dependency_links.txt
src/inmanta_dev_dependencies.egg-info/requires.txt
src/inmanta_dev_dependencies.egg-info/top_level.txt