Metadata-Version: 2.4
Name: inmanta-dev-dependencies
Version: 2.190.0
Summary: Package collecting all common dev dependencies of inmanta modules and extensions to synchronize dependency versions.
Author-email: Inmanta <code@inmanta.com>
Requires-Python: >=3.12
Requires-Dist: black==26.1.0
Requires-Dist: flake8==7.3.0
Requires-Dist: flake8-copyright==0.2.4
Requires-Dist: flake8-black==0.4.0
Requires-Dist: flake8-isort==7.0.0
Requires-Dist: flake8-junit-report==2.1.0
Requires-Dist: isort==7.0.0
Requires-Dist: lxml==6.0.2
Requires-Dist: mypy==1.19.1
Requires-Dist: pep8-naming==0.15.1
Requires-Dist: pytest==9.0.2
Requires-Dist: pyupgrade==3.21.2
Requires-Dist: mypy-baseline==0.7.3
Provides-Extra: module
Requires-Dist: pytest-inmanta; extra == "module"
Provides-Extra: core
Requires-Dist: asyncpg<1.0.0,>=0.21.0; extra == "core"
Requires-Dist: pytest-env==1.2.0; extra == "core"
Requires-Dist: pytest-postgresql==8.0.0; extra == "core"
Requires-Dist: psycopg==3.3.2; extra == "core"
Requires-Dist: tornado<7.0,>=6.1; extra == "core"
Provides-Extra: extension
Requires-Dist: inmanta-core[pytest-inmanta-extensions]; extra == "extension"
Requires-Dist: asyncpg<1.0.0,>=0.21.0; extra == "extension"
Requires-Dist: pytest-env==1.2.0; extra == "extension"
Requires-Dist: pytest-postgresql==8.0.0; extra == "extension"
Requires-Dist: psycopg==3.3.2; extra == "extension"
Requires-Dist: tornado<7.0,>=6.1; extra == "extension"
Provides-Extra: async
Requires-Dist: pytest-asyncio==1.3.0; extra == "async"
Requires-Dist: pytest-timeout==2.4.0; extra == "async"
Provides-Extra: pytest
Requires-Dist: pytest-env==1.2.0; extra == "pytest"
Requires-Dist: pytest-cover==3.0.0; extra == "pytest"
Requires-Dist: pytest-randomly==4.0.1; extra == "pytest"
Requires-Dist: pytest-sugar==1.1.1; extra == "pytest"
Requires-Dist: pytest-instafail==0.5.0; extra == "pytest"
